pp_saturn/__init__.py
pp_saturn/es.py
pp_saturn-0.1.3.dist-info/DESCRIPTION.rst
pp_saturn-0.1.3.dist-info/METADATA
pp_saturn-0.1.3.dist-info/RECORD
pp_saturn-0.1.3.dist-info/WHEEL
pp_saturn-0.1.3.dist-info/metadata.json
pp_saturn-0.1.3.dist-info/top_level.txt
