Metadata-Version: 2.0
Name: pp-saturn
Version: 0.1.3
Summary: PP's Saturn is a collection of python helpers. Saturn (especially Saturn V) was the main vehicle for both manned and unmanned Apollo's missions.
Home-page: https://git.parcelperform.com/dev-team/pp_saturn
Author: Khang Nguyen
Author-email: khang@parcelperform.com
License: UNKNOWN
Platform: UNKNOWN
